qupulse_hdawg_legacy/__about__.py
qupulse_hdawg_legacy/__init__.py
qupulse_hdawg_legacy/seqc.py
qupulse_hdawg_legacy/zihdawg.py
qupulse_hdawg_legacy-0.1.dist-info/METADATA
qupulse_hdawg_legacy-0.1.dist-info/WHEEL
qupulse_hdawg_legacy-0.1.dist-info/licenses/LICENSE.txt
qupulse_hdawg_legacy-0.1.dist-info/RECORD
