Metadata-Version: 2.1
Name: qupulse-hdawg-legacy
Version: 0.1
Summary: Indexed waveform playback based HDAWG driver for qupulse
Project-URL: Documentation, https://github.com/qupulse/qupulse-hdawg-legacy#readme
Project-URL: Issues, https://github.com/qupulse/qupulse-hdawg-legacy/issues
Project-URL: Source, https://github.com/qupulse/qupulse-hdawg-legacy
Author-email: Simon Humpohl <simon.humpohl@rwth-aachen.de>
License-Expression: GPL-3.0
License-File: LICENSE.txt
Classifier: Development Status :: 4 - Beta
Classifier: Programming Language :: Python
Classifier: Programming Language :: Python :: 3.8
Classifier: Programming Language :: Python :: Implementation :: CPython
Classifier: Programming Language :: Python :: Implementation :: PyPy
Requires-Python: <3.9,>=3.8
Requires-Dist: numpy
Requires-Dist: qupulse>=0.9
Requires-Dist: zhinst<=20.7.2701
